Py_reloader.py
__init__.py
setup.py
Py_reloader.py.egg-info/PKG-INFO
Py_reloader.py.egg-info/SOURCES.txt
Py_reloader.py.egg-info/dependency_links.txt
Py_reloader.py.egg-info/requires.txt
Py_reloader.py.egg-info/top_level.txt