Metadata-Version: 2.1
Name: Py-reloader.py
Version: 1.0.0
Summary: ########################################
Author: CODE_BREAKER
Author-email: taneymen2009@gmail.com
